COPYING
MANIFEST.in
setup.py
tail_tools/__init__.py
tail_tools/__main__.py
tail_tools/alternative_tails.py
tail_tools/call_utrs.py
tail_tools/clip_runs.py
tail_tools/env.py
tail_tools/extend_sam.py
tail_tools/fasta_qual_merge.py
tail_tools/primer_gff.py
tail_tools/proportions.py
tail_tools/reference_directory.py
tail_tools/reference_directory_ensembl.py
tail_tools/tail_lengths.py
tail_tools/tail_tools.R
tail_tools/test.py
tail_tools/web.py
tail_tools/workflows.py
tail_tools.egg-info/PKG-INFO
tail_tools.egg-info/SOURCES.txt
tail_tools.egg-info/dependency_links.txt
tail_tools.egg-info/entry_points.txt
tail_tools.egg-info/pbr.json
tail_tools.egg-info/requires.txt
tail_tools.egg-info/top_level.txt
tail_tools/motifer/__init__.py
tail_tools/motifer/pilers.py
tail_tools/motifer/recognizers.py
tail_tools/motifer/reporter.py
tail_tools/motifer/rmonkey.py
tail_tools/web/geneview.html
tail_tools/web/style.css
tail_tools/web/third_party/D3-LICENSE
tail_tools/web/third_party/JQUERY-LICENSE
tail_tools/web/third_party/d3.min.js
tail_tools/web/third_party/jquery.min.js