Metadata-Version: 1.1
Name: tail-tools
Version: 0.42
Summary: Analyse PAT-Seq RNA expression data.
Home-page: http://bioinformatics.net.au/software.tail-tools.shtml
Author: Paul Harrison
Author-email: paul.harrison@monash.edu
License: UNKNOWN
Platform: UNKNOWN
Classifier: License :: OSI Approved :: GNU General Public License v2 or later (GPLv2+)
